ptrc/__init__.py
ptrc/_modidx.py
ptrc/atyp.py
ptrc/cons.py
ptrc/enum.py
ptrc/init.py
ptrc/io.py
ptrc/kwds.py
ptrc/logr.py
ptrc/mask.py
ptrc/pack.py
ptrc/rcur.py
ptrc/slcs.py
ptrc/tens.py
ptrc/util.py
ptrc/vids.py
ptrc-0.0.5.dist-info/LICENSE
ptrc-0.0.5.dist-info/METADATA
ptrc-0.0.5.dist-info/WHEEL
ptrc-0.0.5.dist-info/entry_points.txt
ptrc-0.0.5.dist-info/top_level.txt
ptrc-0.0.5.dist-info/RECORD
