Metadata-Version: 2.1
Name: ptrc
Version: 0.0.5
Summary: In Vitro Fertilization
Home-page: https://github.com/dsm-72/ptrc
Author: dsm-72
Author-email: sumner.magruder@yale.edu
License: Apache Software License 2.0
Keywords: in vitro fertilization ptrc
Classifier: Development Status :: 4 - Beta
Classifier: Intended Audience :: Developers
Classifier: Natural Language :: English
Classifier: Programming Language :: Python :: 3.11
Classifier: License :: OSI Approved :: Apache Software License
Requires-Python: >=3.11
License-File: LICENSE
Requires-Dist: atyp
Requires-Dist: nchr
Requires-Dist: nlit
Requires-Dist: pfmt
Requires-Dist: pstr
Requires-Dist: psrc
Requires-Dist: chck
Requires-Dist: xath
Requires-Dist: nbic
Requires-Dist: asto
Requires-Dist: atup
Requires-Dist: mstar
Requires-Dist: calr
Requires-Dist: fpos
Requires-Dist: ston
Requires-Dist: pttn
Requires-Dist: putl
Provides-Extra: dev
Requires-Dist: numpy ; extra == 'dev'
Requires-Dist: pandas ; extra == 'dev'
Requires-Dist: matplotlib ; extra == 'dev'
Requires-Dist: torch ; extra == 'dev'
Requires-Dist: pytorch-lightning ; extra == 'dev'
Requires-Dist: torchvision ; extra == 'dev'
